ncolor/__init__.py
ncolor/_version.py
ncolor/format_labels.py
ncolor/label.py
ncolor-1.5.3.dist-info/licenses/LICENSE
ncolor-1.5.3.dist-info/METADATA
ncolor-1.5.3.dist-info/WHEEL
ncolor-1.5.3.dist-info/top_level.txt
ncolor-1.5.3.dist-info/RECORD
