Metadata-Version: 2.4
Name: ncolor
Version: 1.5.3
Summary: label matrix coloring algorithm
Home-page: https://github.com/kevinjohncutler/ncolor
Author: Kevin Cutler
Author-email: kevinjohncutler@outlook.com
License: BSD
Classifier: Programming Language :: Python :: 3
Classifier: License :: OSI Approved :: BSD License
Classifier: Operating System :: OS Independent
License-File: LICENSE
Requires-Dist: numba>=0.60.0
Requires-Dist: scipy
Requires-Dist: fastremap
Requires-Dist: scikit-image
Requires-Dist: mahotas>=1.4.13
Dynamic: author
Dynamic: author-email
Dynamic: classifier
Dynamic: description
Dynamic: description-content-type
Dynamic: home-page
Dynamic: license
Dynamic: license-file
Dynamic: requires-dist
Dynamic: summary
